carrotlite/__init__.py
carrotlite/_version.py
carrotlite/clilite/__init__.py
carrotlite/clilite/command.py
carrotlite/clilite/subcommands/__init__.py
carrotlite/clilite/subcommands/run.py
carrotlite/config/OMOPCDM_postgresql_5.3_ddl.sql
carrotlite/config/omop.json
carrotlite/tools/__init__.py
carrotlite/tools/file_helpers.py
carrotlite/tools/mappingrules.py
carrotlite/tools/metrics.py
carrotlite/tools/omopcdm.py
clilite/__init__.py
clilite/command.py
clilite/subcommands/__init__.py
clilite/subcommands/run.py
config/OMOPCDM_postgresql_5.3_ddl.sql
config/omop.json
tools/__init__.py
tools/file_helpers.py
tools/mappingrules.py
tools/metrics.py
tools/omopcdm.py
carrotlite-0.3.dist-info/LICENSE
carrotlite-0.3.dist-info/METADATA
carrotlite-0.3.dist-info/WHEEL
carrotlite-0.3.dist-info/entry_points.txt
carrotlite-0.3.dist-info/top_level.txt
carrotlite-0.3.dist-info/RECORD
